cbitstruct/_cbitstruct.cpython-312-x86_64-linux-gnu.so
cbitstruct/__init__.py
cbitstruct/tests/test_perf.py
cbitstruct/tests/test_cornercase.py
cbitstruct/tests/test_against_bitstruct.py
cbitstruct/tests/__init__.py
cbitstruct/tests/test_bitstruct.py
cbitstruct/tests/test_api.py
cbitstruct-1.1.1.dist-info/LICENSE.md
cbitstruct-1.1.1.dist-info/METADATA
cbitstruct-1.1.1.dist-info/RECORD
cbitstruct-1.1.1.dist-info/WHEEL
cbitstruct-1.1.1.dist-info/top_level.txt
