Metadata-Version: 2.1
Name: cbitstruct
Version: 1.1.1
Summary: Faster C implementation of bitstruct
Home-page: https://github.com/qchateau/cbitstruct
Author: Quentin CHATEAU
Author-email: quentin.chateau@gmail.com
License: MPL-2.0
Keywords: bit,pack,unpack,struct,bitfield,bit parsing,bit unpack,bit pack,C
Classifier: Programming Language :: Python :: 3
Classifier: Programming Language :: C
Classifier: License :: OSI Approved :: Mozilla Public License 2.0 (MPL 2.0)
Classifier: Operating System :: OS Independent
Requires-Python: >=3.6
License-File: LICENSE.md
Provides-Extra: test
Requires-Dist: bitstruct; extra == "test"
